{"total":"45487","name":"比亚迪","url":"/pic/brand-75.html","models":[{"id":"146","type":"比亚迪","url":"/pic/brand-75-146.html","model":[{"id":"579","total":"2759","status":"在售","name":"比亚迪F0 ","url":"/pic/series/579.html"},{"id":"4073","total":"558","status":"在售","name":"比亚迪e5 ","url":"/pic/series/4073.html"},{"id":"407","total":"3674","status":"在售","name":"比亚迪F3 ","url":"/pic/series/407.html"},{"id":"3283","total":"1353","status":"在售","name":"比亚迪G5 ","url":"/pic/series/3283.html"},{"id":"2761","total":"2965","status":"在售","name":"秦 ","url":"/pic/series/2761.html"},{"id":"2806","total":"3839","status":"在售","name":"速锐 ","url":"/pic/series/2806.html"},{"id":"3781","total":"1733","status":"在售","name":"元 ","url":"/pic/series/3781.html"},{"id":"4353","total":"345","status":"在售","name":"元新能源 ","url":"/pic/series/4353.html"},{"id":"3780","total":"2252","status":"在售","name":"宋 ","url":"/pic/series/3780.html"},{"id":"4394","total":"835","status":"在售","name":"宋新能源 ","url":"/pic/series/4394.html"},{"id":"3059","total":"2776","status":"在售","name":"比亚迪S7 ","url":"/pic/series/3059.html"},{"id":"3430","total":"1173","status":"在售","name":"唐 ","url":"/pic/series/3430.html"},{"id":"831","total":"1861","status":"在售","name":"比亚迪e6 ","url":"/pic/series/831.html"},{"id":"798","total":"2126","status":"在售","name":"比亚迪M6 ","url":"/pic/series/798.html"},{"id":"4279","total":"1144","status":"在售","name":"宋MAX ","url":"/pic/series/4279.html"},{"id":"2088","total":"5050","status":"在售","name":"比亚迪S6 ","url":"/pic/series/2088.html"},{"id":"4393","total":"43","status":"在售","name":"王朝概念车 ","url":"/pic/series/4393.html"},{"id":"3474","total":"78","status":"在售","name":"商 ","url":"/pic/series/3474.html"},{"id":"417","total":"81","status":"停售","name":"福莱尔 ","url":"/pic/series/417.html"},{"id":"940","total":"1393","status":"停售","name":"比亚迪F3R ","url":"/pic/series/940.html"},{"id":"4333","total":"294","status":"停售","name":"比亚迪F3新能源 ","url":"/pic/series/4333.html"},{"id":"927","total":"1232","status":"停售","name":"比亚迪G3 ","url":"/pic/series/927.html"},{"id":"997","total":"532","status":"停售","name":"比亚迪G3R ","url":"/pic/series/997.html"},{"id":"2085","total":"1782","status":"停售","name":"比亚迪L3 ","url":"/pic/series/2085.html"},{"id":"540","total":"1062","status":"停售","name":"比亚迪F6 ","url":"/pic/series/540.html"},{"id":"2091","total":"3237","status":"停售","name":"比亚迪G6 ","url":"/pic/series/2091.html"},{"id":"2944","total":"1103","status":"停售","name":"思锐 ","url":"/pic/series/2944.html"},{"id":"489","total":"207","status":"停售","name":"比亚迪S8 ","url":"/pic/series/489.html"}]}]}